alexcanc_de_toolkit/__init__.py
alexcanc_de_toolkit/main.py
alexcanc_de_toolkit/vm.py
alexcanc_de_toolkit-0.1.0.dist-info/METADATA
alexcanc_de_toolkit-0.1.0.dist-info/WHEEL
alexcanc_de_toolkit-0.1.0.dist-info/entry_points.txt
alexcanc_de_toolkit-0.1.0.dist-info/RECORD
